presidio_anonymizer/__init__.py
presidio_anonymizer/anonymizer_engine.py
presidio_anonymizer/batch_anonymizer_engine.py
presidio_anonymizer/core/__init__.py
presidio_anonymizer/core/engine_base.py
presidio_anonymizer/core/text_replace_builder.py
presidio_anonymizer/deanonymize_engine.py
presidio_anonymizer/entities/__init__.py
presidio_anonymizer/entities/conflict_resolution_strategy.py
presidio_anonymizer/entities/engine/__init__.py
presidio_anonymizer/entities/engine/dict_recognizer_result.py
presidio_anonymizer/entities/engine/operator_config.py
presidio_anonymizer/entities/engine/pii_entity.py
presidio_anonymizer/entities/engine/recognizer_result.py
presidio_anonymizer/entities/engine/result/__init__.py
presidio_anonymizer/entities/engine/result/engine_result.py
presidio_anonymizer/entities/engine/result/operator_result.py
presidio_anonymizer/entities/invalid_exception.py
presidio_anonymizer/operators/__init__.py
presidio_anonymizer/operators/aes_cipher.py
presidio_anonymizer/operators/custom.py
presidio_anonymizer/operators/deanonymize_keep.py
presidio_anonymizer/operators/decrypt.py
presidio_anonymizer/operators/encrypt.py
presidio_anonymizer/operators/hash.py
presidio_anonymizer/operators/keep.py
presidio_anonymizer/operators/mask.py
presidio_anonymizer/operators/operator.py
presidio_anonymizer/operators/operators_factory.py
presidio_anonymizer/operators/redact.py
presidio_anonymizer/operators/replace.py
presidio_anonymizer/py.typed
presidio_anonymizer/services/__init__.py
presidio_anonymizer/services/app_entities_convertor.py
presidio_anonymizer/services/validators.py
presidio_anonymizer-2.2.359.dist-info/METADATA
presidio_anonymizer-2.2.359.dist-info/WHEEL
presidio_anonymizer-2.2.359.dist-info/RECORD
