Metadata-Version: 2.3
Name: presidio_anonymizer
Version: 2.2.359
Summary: Presidio Anonymizer package - replaces analyzed text with desired values.
License: MIT
Keywords: presidio_anonymizer
Author: Presidio
Author-email: presidio@microsoft.com
Requires-Python: >=3.9,<4.0
Classifier: License :: OSI Approved :: MIT License
Classifier: Operating System :: OS Independent
Classifier: Programming Language :: Python :: 3.9
Classifier: Programming Language :: Python :: 3.10
Classifier: Programming Language :: Python :: 3.11
Classifier: Programming Language :: Python :: 3.12
Provides-Extra: server
Requires-Dist: cryptography (<44.1)
Requires-Dist: flask (>=1.1) ; extra == "server"
Requires-Dist: gunicorn ; extra == "server"
Project-URL: Homepage, https://github.com/Microsoft/presidio
